{
  "skinList": [
    {
      "name": "Default"
    },
    {
      "name": "Default (Red)"
    },
    {
      "name": "Default (Blue)"
    },
    {
      "name": "Default (Green)"
    },
    {
      "name": "Default (Mint)"
    },
    {
      "name": "Default (Purple)"
    },
    {
      "name": "Default (Black)"
    },
    {
      "name": "Default (Spooky)"
    },
    {
      "name": "Default (Cool Blue)"
    },
    {
      "name": "Soccer"
    },
    {
      "name": "Soccer (Red)"
    },
    {
      "name": "Soccer (Blue)"
    },
    {
      "name": "Soccer (Green)"
    },
    {
      "name": "Goliath"
    },
    {
      "name": "Goliath (Red)"
    },
    {
      "name": "Goliath (Blue)"
    },
    {
      "name": "Goliath (Green)"
    },
    {
      "name": "Abyss"
    },
    {
      "name": "Abyss (Red)"
    },
    {
      "name": "Abyss (Blue)"
    },
    {
      "name": "Abyss (Green)"
    },
    {
      "name": "Retro"
    },
    {
      "name": "Retro (Red)"
    },
    {
      "name": "Retro (Blue)"
    },
    {
      "name": "Retro (Green)"
    },
    {
      "name": "Retro (Black)"
    },
    {
      "name": "LadyBug"
    },
    {
      "name": "LadyBug (Red)"
    },
    {
      "name": "LadyBug (Blue)"
    },
    {
      "name": "LadyBug (Green)"
    },
    {
      "name": "Scarab"
    },
    {
      "name": "Scarab (Red)"
    },
    {
      "name": "Scarab (Blue)"
    },
    {
      "name": "Scarab (Green)"
    },
    {
      "name": "Low Poly"
    },
    {
      "name": "Low Poly (Red)"
    },
    {
      "name": "Low Poly (Blue)"
    },
    {
      "name": "Low Poly (Green)"
    }
  ],
    "scoreboard": {
        "neutral": {
            "x": 2,
            "y": 18,
            "scale": 2.0
        }
    },
    "vsScreen": {
        "neutral": {
            "x": -590,
            "y": 50,
            "scale": 1.25
        }
    },
    "gui": {
        "neutral": {
            "x": 5,
            "y": -5,
            "scale": 0.85
        }
    }
}
